pythautomata/__init__.py
pythautomata/abstract/__init__.py
pythautomata/abstract/boolean_model.py
pythautomata/abstract/finite_automaton.py
pythautomata/abstract/model.py
pythautomata/abstract/model_exporting_strategy.py
pythautomata/abstract/pdfa_model_exporting_strategy.py
pythautomata/abstract/probabilistic_model.py
pythautomata/automata/__init__.py
pythautomata/automata/deterministic_finite_automaton.py
pythautomata/automata/mealy_machine.py
pythautomata/automata/moore_machine_automaton.py
pythautomata/automata/non_deterministic_finite_automaton.py
pythautomata/automata/symbolic_finite_automaton.py
pythautomata/automata/wheighted_automaton_definition/probabilistic_deterministic_finite_automaton.py
pythautomata/automata/wheighted_automaton_definition/weighted_automaton.py
pythautomata/automata/wheighted_automaton_definition/weighted_state.py
pythautomata/automata/wheighted_automaton_definition/weighted_transition.py
pythautomata/automata_definitions/__init__.py
pythautomata/automata_definitions/bollig_habermehl_kern_leucker_automata.py
pythautomata/automata_definitions/omlin_giles_automata.py
pythautomata/automata_definitions/other_automata.py
pythautomata/automata_definitions/sample_mealy_machines.py
pythautomata/automata_definitions/sample_moore_machines.py
pythautomata/automata_definitions/sample_nfas.py
pythautomata/automata_definitions/tomitas_grammars.py
pythautomata/automata_definitions/tomitas_grammars_modifications.py
pythautomata/automata_definitions/weighted_tomitas_grammars.py
pythautomata/automata_definitions/weighted_tomitas_grammars_with_zero_transitions.py
pythautomata/automata_definitions/zero_transitions_examples.py
pythautomata/base_types/__init__.py
pythautomata/base_types/alphabet.py
pythautomata/base_types/guard.py
pythautomata/base_types/mealy_state.py
pythautomata/base_types/moore_state.py
pythautomata/base_types/sequence.py
pythautomata/base_types/state.py
pythautomata/base_types/symbol.py
pythautomata/base_types/symbolic_state.py
pythautomata-0.41.0.dist-info/LICENSE
pythautomata-0.41.0.dist-info/METADATA
pythautomata-0.41.0.dist-info/WHEEL
pythautomata-0.41.0.dist-info/RECORD
