Metadata-Version: 2.3
Name: pythautomata
Version: 0.41.0
Summary: ORT's implementation of various kinds of automata
Author: Federico Vilensky
Author-email: fedevilensky@gmail.com
Requires-Python: >=3.9,<3.11
Classifier: Programming Language :: Python :: 3
Classifier: Programming Language :: Python :: 3.9
Classifier: Programming Language :: Python :: 3.10
Requires-Dist: graphviz
Requires-Dist: numpy
Requires-Dist: pydot (>=1.4.2,<2.0.0)
Requires-Dist: scikit-learn (>=1.2.1,<2.0.0)
Requires-Dist: scipy (>=1.7.3,<2.0.0)
